rubin/nublado/client/__init__.py
rubin/nublado/client/_asyncio.py
rubin/nublado/client/_client.py
rubin/nublado/client/_exceptions.py
rubin/nublado/client/_http.py
rubin/nublado/client/_mock.py
rubin/nublado/client/_models.py
rubin/nublado/client/_session.py
rubin/nublado/client/py.typed
rubin_nublado_client-11.2.1.dist-info/licenses/LICENSE
rubin_nublado_client-11.2.1.dist-info/METADATA
rubin_nublado_client-11.2.1.dist-info/WHEEL
rubin_nublado_client-11.2.1.dist-info/top_level.txt
rubin_nublado_client-11.2.1.dist-info/RECORD
