Metadata-Version: 2.4
Name: rubin-nublado-client
Version: 11.2.1
Summary: Client for JupyterHub/JupyterLab in the Rubin Science Platform context
License-Expression: MIT
Project-URL: Homepage, https://nublado.lsst.io
Project-URL: Source, https://github.com/lsst-sqre/nublado
Project-URL: Change log, https://nublado.lsst.io/changelog.html
Project-URL: Issue tracker, https://github.com/lsst-sqre/nublado/issues
Keywords: rubin,lsst
Classifier: Development Status :: 5 - Production/Stable
Classifier: Programming Language :: Python
Classifier: Programming Language :: Python :: 3
Classifier: Programming Language :: Python :: 3.12
Classifier: Programming Language :: Python :: 3.13
Classifier: Programming Language :: Python :: 3.14
Classifier: Intended Audience :: Developers
Classifier: Natural Language :: English
Classifier: Operating System :: POSIX
Classifier: Typing :: Typed
Requires-Python: >=3.13
License-File: LICENSE
Requires-Dist: httpx<1
Requires-Dist: httpx-sse<1,>=0.4.1
Requires-Dist: pydantic<3,>2.11
Requires-Dist: rubin-gafaelfawr
Requires-Dist: rubin-repertoire<1
Requires-Dist: safir<15
Requires-Dist: structlog
Requires-Dist: websockets<17,>=14
Dynamic: license-file
